{
  "file_name": "dpl__forst:rough.pl",
  "run_index": 1,
  "Validity_form": false,
  "Validity_result": false,
  "running_time": 51,
  "iter_count": 1,
  "process_time": 51.08543682098389,
  "final_result": "% Problog Inference Result：\nstack_op(push(1),[2, 3, 4],X2) = 0.0000\nstack_op(pop,[1, 2, 3, 4],X2) = 0.0000\nstack_op(dup,[1, 2, 3, 4],X2) = 0.0000\nstack_op(swap,[1, 2, 3, 4],X2) = 0.0000\nstack_op(over,[1, 2, 3, 4],X2) = 0.0000\nstack_op(rot,[1, 2, 3, 4],X2) = 0.0000",
  "final_report": "The generated code is incomplete and incorrect. It lacks the essential stack operation predicates (push, pop, dup, swap, over, rot) that were present in the original code. The generated code only includes the 'sort' operation and its helper predicates, which are duplicated unnecessarily. As a result, the queries fail to produce the expected results, returning 0.0000 probabilities for all operations. The generated code does not meet the requirements as it cannot perform the basic stack operations that the original code could."
}