{
  "file_name": "pl___robot:precise.pl",
  "runs": 5,
  "avg_process_time": 64.77592434883118,
  "min_process_time": 52.10054588317871,
  "max_process_time": 73.50651693344116,
  "std_dev_time": 7.862289462329788,
  "success_form_count": 5,
  "success_result_count": 5,
  "invalid_form_count": 0,
  "invalid_result_count": 0,
  "error_count": 0,
  "success_form_rate": 1.0,
  "success_result_rate": 1.0,
  "individual_results": [
    {
      "file_name": "pl___robot:precise.pl",
      "run_index": 1,
      "Validity_form": true,
      "Validity_result": true,
      "running_time": 74,
      "iter_count": 3,
      "process_time": 73.50651693344116
    },
    {
      "file_name": "pl___robot:precise.pl",
      "run_index": 2,
      "Validity_form": true,
      "Validity_result": true,
      "running_time": 66,
      "iter_count": 3,
      "process_time": 66.45843720436096
    },
    {
      "file_name": "pl___robot:precise.pl",
      "run_index": 3,
      "Validity_form": true,
      "Validity_result": true,
      "running_time": 52,
      "iter_count": 2,
      "process_time": 52.10054588317871
    },
    {
      "file_name": "pl___robot:precise.pl",
      "run_index": 4,
      "Validity_form": true,
      "Validity_result": true,
      "running_time": 64,
      "iter_count": 3,
      "process_time": 64.32843375205994
    },
    {
      "file_name": "pl___robot:precise.pl",
      "run_index": 5,
      "Validity_form": true,
      "Validity_result": true,
      "running_time": 67,
      "iter_count": 3,
      "process_time": 67.48568797111511
    }
  ]
}