{
  "file_name": "dpl__hfw__:rough.pl",
  "Validity_form": true,
  "Validity_result": false,
  "running_time": 326,
  "iter_count": 3,
  "process_time": 325.93025732040405,
  "final_result": "% Problog Inference Result：\nexpression([image_2, image_divide, image_3, image_plus, image_3, image_minus, image_2, image_multiply, image_7],-0.25) = 1.0000",
  "final_report": "The generated code has a different parsing logic for mathematical expressions compared to the original code. While the original code correctly handles operator precedence by using recursive parsing with intermediate results, the generated code processes operations left-to-right without proper precedence handling. This leads to incorrect calculation results, as seen in the different outputs (-10.333 vs -0.25). The generated code's form is valid Prolog syntax but fails to implement the correct mathematical evaluation logic."
}