{
  "file_name": "dpl__addit:partial.pl",
  "runs": 5,
  "avg_process_time": 24.479570817947387,
  "min_process_time": 22.661290884017944,
  "max_process_time": 27.156129837036133,
  "std_dev_time": 1.6634501528225025,
  "success_form_count": 4,
  "success_result_count": 3,
  "invalid_form_count": 1,
  "invalid_result_count": 2,
  "error_count": 0,
  "success_form_rate": 0.8,
  "success_result_rate": 0.6,
  "individual_results": [
    {
      "file_name": "dpl__addit:partial.pl",
      "run_index": 1,
      "Validity_form": false,
      "Validity_result": false,
      "running_time": 24,
      "iter_count": 0,
      "process_time": 24.480996131896973
    },
    {
      "file_name": "dpl__addit:partial.pl",
      "run_index": 2,
      "Validity_form": true,
      "Validity_result": true,
      "running_time": 23,
      "iter_count": 0,
      "process_time": 22.661290884017944
    },
    {
      "file_name": "dpl__addit:partial.pl",
      "run_index": 3,
      "Validity_form": true,
      "Validity_result": false,
      "running_time": 27,
      "iter_count": 0,
      "process_time": 27.156129837036133
    },
    {
      "file_name": "dpl__addit:partial.pl",
      "run_index": 4,
      "Validity_form": true,
      "Validity_result": true,
      "running_time": 24,
      "iter_count": 0,
      "process_time": 23.71163010597229
    },
    {
      "file_name": "dpl__addit:partial.pl",
      "run_index": 5,
      "Validity_form": true,
      "Validity_result": true,
      "running_time": 24,
      "iter_count": 0,
      "process_time": 24.3878071308136
    }
  ]
}